PyRoGap/__init__.py
PyRoGap/form.py
PyRoGap/gap_bot.py
PyRoGap/get_chat_gap.py
PyRoGap/inline_keyboard.py
PyRoGap/message.py
PyRoGap/reply_keyboard_markup.py
pyrogap-1.1.0.dist-info/licenses/LICENSE
pyrogap-1.1.0.dist-info/METADATA
pyrogap-1.1.0.dist-info/WHEEL
pyrogap-1.1.0.dist-info/top_level.txt
pyrogap-1.1.0.dist-info/RECORD
