Metadata-Version: 2.4
Name: PyRoGap
Version: 1.1.0
Summary: This library helps you in building bots on the Gap messenger. PyRoGap is one of the best bot development libraries for Gap, and with it, you can create various types of bots. 🐍✨
Home-page: https://pyrogap.pythonanywhere.com/
Author: MohammadReza
Author-email: narnama.room@gmail.com
Project-URL: مستندات کتابخانه 📚, https://pyrogap.pythonanywhere.com/
Project-URL: صفحه من ❤️, https://apicode.pythonanywhere.com/
Project-URL: مستندات ربات های گپ 📚, https://my.gap.im/doc/botplatform
Project-URL: کانال مستندات 📜, https://gap.im/PyRoGap
Classifier: Programming Language :: Python :: 3
Classifier: License :: OSI Approved :: MIT License
Classifier: Operating System :: OS Independent
Requires-Python: >=3.5
License-File: LICENSE
Requires-Dist: requests
Requires-Dist: beautifulsoup4
Dynamic: author
Dynamic: author-email
Dynamic: classifier
Dynamic: description
Dynamic: description-content-type
Dynamic: home-page
Dynamic: license-file
Dynamic: project-url
Dynamic: requires-dist
Dynamic: requires-python
Dynamic: summary
